dendrotweaks/__init__.py
dendrotweaks/model.py
dendrotweaks/model_io.py
dendrotweaks/model_simulation.py
dendrotweaks/path_manager.py
dendrotweaks/prerun.py
dendrotweaks/simulators.py
dendrotweaks/utils.py
dendrotweaks/analysis/__init__.py
dendrotweaks/analysis/ephys_analysis.py
dendrotweaks/analysis/morphometric_analysis.py
dendrotweaks/biophys/__init__.py
dendrotweaks/biophys/distributions.py
dendrotweaks/biophys/groups.py
dendrotweaks/biophys/mechanisms.py
dendrotweaks/biophys/default_mod/AMPA.mod
dendrotweaks/biophys/default_mod/AMPA_NMDA.mod
dendrotweaks/biophys/default_mod/CaDyn.mod
dendrotweaks/biophys/default_mod/GABAa.mod
dendrotweaks/biophys/default_mod/Leak.mod
dendrotweaks/biophys/default_mod/NMDA.mod
dendrotweaks/biophys/default_mod/vecstim.mod
dendrotweaks/biophys/default_templates/NEURON_template.py
dendrotweaks/biophys/default_templates/default.py
dendrotweaks/biophys/default_templates/jaxley.py
dendrotweaks/biophys/default_templates/standard_channel.mod
dendrotweaks/biophys/default_templates/template_jaxley.py
dendrotweaks/biophys/default_templates/template_jaxley_new.py
dendrotweaks/biophys/io/__init__.py
dendrotweaks/biophys/io/ast.py
dendrotweaks/biophys/io/code_generators.py
dendrotweaks/biophys/io/converter.py
dendrotweaks/biophys/io/factories.py
dendrotweaks/biophys/io/grammar.py
dendrotweaks/biophys/io/loader.py
dendrotweaks/biophys/io/parser.py
dendrotweaks/biophys/io/reader.py
dendrotweaks/morphology/__init__.py
dendrotweaks/morphology/domains.py
dendrotweaks/morphology/point_trees.py
dendrotweaks/morphology/sec_trees.py
dendrotweaks/morphology/seg_trees.py
dendrotweaks/morphology/trees.py
dendrotweaks/morphology/io/__init__.py
dendrotweaks/morphology/io/factories.py
dendrotweaks/morphology/io/reader.py
dendrotweaks/morphology/io/validation.py
dendrotweaks/morphology/reduce/__init__.py
dendrotweaks/morphology/reduce/reduce.py
dendrotweaks/morphology/reduce/reduced_cylinder.py
dendrotweaks/stimuli/__init__.py
dendrotweaks/stimuli/iclamps.py
dendrotweaks-0.5.1.dist-info/licenses/LICENSE
dendrotweaks-0.5.1.dist-info/METADATA
dendrotweaks-0.5.1.dist-info/WHEEL
dendrotweaks-0.5.1.dist-info/top_level.txt
dendrotweaks-0.5.1.dist-info/RECORD
