Metadata-Version: 2.4
Name: dendrotweaks
Version: 0.5.1
Summary: A toolbox for exploring dendritic dynamics
Home-page: https://dendrotweaks.dendrites.gr
Author: Roman Makarov
Author-email: dendrotweaks@dendrites.gr
License: Mozilla Public License 2.0 (MPL 2.0)
Project-URL: Source, https://github.com/Poirazi-Lab/DendroTweaks
Project-URL: Documentation, https://dendrotweaks.readthedocs.io/
Keywords: dendrites,neuron,model,simulation,neuroscience
Classifier: Programming Language :: Python :: 3
Classifier: License :: OSI Approved :: Mozilla Public License 2.0 (MPL 2.0)
Classifier: Operating System :: OS Independent
Requires-Python: >=3.9
License-File: LICENSE
Requires-Dist: neuron>=8.2.6; sys_platform == "linux" or sys_platform == "darwin"
Requires-Dist: neuron-reduce==0.0.7
Requires-Dist: numpy<2.0.0
Requires-Dist: pandas
Requires-Dist: pyparsing
Requires-Dist: symfit
Requires-Dist: matplotlib
Requires-Dist: scipy
Requires-Dist: jinja2
Requires-Dist: quantities
Provides-Extra: dev
Requires-Dist: sphinx; extra == "dev"
Requires-Dist: furo; extra == "dev"
Requires-Dist: sphinx-copybutton; extra == "dev"
Requires-Dist: build; extra == "dev"
Dynamic: license-file
